scmallet/__init__.py
scmallet/binarize.py
scmallet/eval_model.py
scmallet/infer.py
scmallet/input.py
scmallet/mallet.py
scmallet/topic_metrices.py
scmallet/utils.py
scmallet-0.1.2.dist-info/METADATA
scmallet-0.1.2.dist-info/WHEEL
scmallet-0.1.2.dist-info/licenses/LICENSE
scmallet-0.1.2.dist-info/RECORD
