Metadata-Version: 2.3
Name: scmallet
Version: 0.1.2
Summary: Python wrapper of MALLET for LDA analysis on single-cell data
Project-URL: Source, https://github.com/lhqing/scmallet
Project-URL: Home-page, https://github.com/lhqing/scmallet
Author: Hanqing Liu
Maintainer-email: Hanqing Liu <hanqingliu@fas.harvard.edu>
License: MIT License
License-File: LICENSE
Requires-Python: >=3.9
Requires-Dist: anndata
Requires-Dist: gensim
Requires-Dist: numpy
Requires-Dist: pandas
Requires-Dist: pyranges
Requires-Dist: scipy<1.13
Provides-Extra: dev
Requires-Dist: pre-commit; extra == 'dev'
Requires-Dist: twine>=4.0.2; extra == 'dev'
Provides-Extra: test
Requires-Dist: coverage; extra == 'test'
Requires-Dist: pytest; extra == 'test'
